lamapi/__init__.py
lamapi/app.py
lamapi/config.py
lamapi/exceptions.py
lamapi/middlewares.py
lamapi/utils.py
lamapi/wrappers.py
Lamapi-0.1.7.dist-info/METADATA
Lamapi-0.1.7.dist-info/WHEEL
Lamapi-0.1.7.dist-info/top_level.txt
Lamapi-0.1.7.dist-info/RECORD
